<?xml version="1.0" encoding="utf-8" ?>
<dwsync>
<file name="checkbox.php" server="ftp.bigmikestudios.com/public_html/wptemplate/" local="129606113400000000" remote="129606113400000000" />
<file name="file.php" server="ftp.bigmikestudios.com/public_html/wptemplate/" local="129606113400000000" remote="129606113400000000" />
<file name="file_meta.php" server="ftp.bigmikestudios.com/public_html/wptemplate/" local="129606113400000000" remote="129606113400000000" />
<file name="radio.php" server="ftp.bigmikestudios.com/public_html/wptemplate/" local="129606113400000000" remote="129606113400000000" />
<file name="select.php" server="ftp.bigmikestudios.com/public_html/wptemplate/" local="129606113400000000" remote="129606113400000000" />
<file name="text.php" server="ftp.bigmikestudios.com/public_html/wptemplate/" local="129606113400000000" remote="129606113400000000" />
<file name="textarea.php" server="ftp.bigmikestudios.com/public_html/wptemplate/" local="129606113400000000" remote="129606113400000000" />
<file name="file.php" server="ftp.bigmikestudios.com/public_html/engagingresources/" local="129685515392907049" remote="129685606800000000" />
<file name="editor.php" server="ftp.bigmikestudios.com/public_html/aerco/" local="129987860596786894" remote="129991417800000000" />
<file name="relationship.php" server="ftp.bigmikestudios.com/public_html/aerco/" local="129997312629838921" remote="129999193200000000" />
<file name="file_meta.php" server="ftp.bigmikestudios.com/public_html/aerco/" local="129997472935267867" remote="129999193200000000" />
<file name="text-multiple.php" server="ftp.bigmikestudios.com/public_html/aerco/" local="129996512744788113" remote="129999193200000000" />
<file name="text.php" server="ftp.bigmikestudios.com/public_html/aerco/" local="129996493025480233" remote="129999193200000000" />
</dwsync>